examples/__init__.py
examples/test.py
ssr_eval/__init__.py
ssr_eval/dsp.py
ssr_eval/eval.py
ssr_eval/lowpass.py
ssr_eval/metrics.py
ssr_eval/test.py
ssr_eval/utils.py
ssr_eval-0.0.7.dist-info/METADATA
ssr_eval-0.0.7.dist-info/WHEEL
ssr_eval-0.0.7.dist-info/top_level.txt
ssr_eval-0.0.7.dist-info/RECORD
