Metadata-Version: 2.1
Name: ssr-eval
Version: 0.0.7
Summary: This package is written for the evaluation of speech super-resolution algorithms.
Home-page: https://github.com/haoheliu/ssr_eval
Author: Haohe Liu
Author-email: haoheliu@gmail.com
License: MIT
Classifier: License :: OSI Approved :: MIT License
Classifier: Programming Language :: Python
Classifier: Programming Language :: Python :: 3
Classifier: Programming Language :: Python :: 3.7
Classifier: Programming Language :: Python :: Implementation :: CPython
Classifier: Programming Language :: Python :: Implementation :: PyPy
Requires-Python: >=3.6.0
Requires-Dist: tqdm
Requires-Dist: librosa
Requires-Dist: soundfile
Requires-Dist: scikit-image
Requires-Dist: wave
Requires-Dist: torch (>=1.6.0)
Requires-Dist: torchlibrosa (>=0.0.7)
